utpy/__init__.py
utpy/decipher.py
utpy/dicts.py
utpy/exceptions.py
utpy/test.py
utpy/utpy.py
utpy-2.4.0.dist-info/METADATA
utpy-2.4.0.dist-info/WHEEL
utpy-2.4.0.dist-info/top_level.txt
utpy-2.4.0.dist-info/RECORD
