Metadata-Version: 2.1
Name: utpy
Version: 2.4.0
Summary: youtube downloader python package
Home-page: https://github.com/tare9n/utpy
Author: Taregh Naderi
Author-email: taregh.n@gmail.com
License: UNKNOWN
Platform: UNKNOWN
Classifier: Programming Language :: Python :: 3
Classifier: License :: OSI Approved :: MIT License
Classifier: Operating System :: OS Independent
Requires-Python: >=3.7
